{"frames": {

"base0000":
{
	"frame": {"x":0,"y":0,"w":195,"h":70},
	"rotated": false,
	"trimmed": false,
	"spriteSourceSize": {"x":0,"y":0,"w":195,"h":70},
	"sourceSize": {"w":195,"h":70}
},
"mag0000":
{
	"frame": {"x":197,"y":0,"w":16,"h":73},
	"rotated": false,
	"trimmed": false,
	"spriteSourceSize": {"x":0,"y":0,"w":16,"h":73},
	"sourceSize": {"w":16,"h":73}
}},
"meta": {
	"app": "Adobe Animate",
	"version": "16.5.0.100",
	"image": "atlas_mp9.png",
	"format": "RGBA8888",
	"size": {"w":256,"h":256},
	"scale": "1"
}
}
